efa_utils/__init__.py
efa_utils/efa_utils_functions.py
efa_utils-0.8.6.dist-info/LICENSE
efa_utils-0.8.6.dist-info/METADATA
efa_utils-0.8.6.dist-info/WHEEL
efa_utils-0.8.6.dist-info/RECORD
