Metadata-Version: 2.1
Name: efa_utils
Version: 0.8.6
Summary: Custom utility functions for exploratory factor analysis with the factor_analyzer package.
License: GNU General Public License v3.0
Author: Marcel Wiechmann
Author-email: mail@mwiechmann.com
Requires-Python: >=3.9
Classifier: License :: Other/Proprietary License
Classifier: Programming Language :: Python :: 3
Classifier: Programming Language :: Python :: 3.9
Classifier: Programming Language :: Python :: 3.10
Classifier: Programming Language :: Python :: 3.11
Classifier: Programming Language :: Python :: 3.12
Provides-Extra: optional
Requires-Dist: factor-analyzer (>=0.5.1,<0.6.0)
Requires-Dist: numpy (>=1.23.5,<2.0.0)
Requires-Dist: pandas (>=2.1.0,<3.0.0)
Requires-Dist: statsmodels (>=0.14.0,<0.15.0)
